rst_pypi_ref/__init__.py
rst_pypi_ref/cli.py
rst_pypi_ref/core.py
rst_pypi_ref/sphinx.py
rst_pypi_ref-0.4.0.dist-info/LICENSE
rst_pypi_ref-0.4.0.dist-info/WHEEL
rst_pypi_ref-0.4.0.dist-info/METADATA
rst_pypi_ref-0.4.0.dist-info/RECORD
