Metadata-Version: 2.1
Name: rst-pypi-ref
Version: 0.4.0
Summary: reStructuredText custom role to add ref to PyPI.
Author-email: Kazuya Takei <myself@attakei.net>
Requires-Python: >= 3.9
Classifier: Development Status :: 3 - Alpha
Classifier: Framework :: Sphinx
Classifier: Intended Audience :: Developers
Classifier: License :: OSI Approved :: Apache Software License
Classifier: Operating System :: OS Independent
Classifier: Programming Language :: Python
Classifier: Programming Language :: Python :: 3
Classifier: Programming Language :: Python :: 3 :: Only
Classifier: Programming Language :: Python :: 3.9
Classifier: Programming Language :: Python :: 3.10
Classifier: Programming Language :: Python :: 3.11
Classifier: Programming Language :: Python :: 3.12
Classifier: Topic :: Documentation :: Sphinx
Classifier: Topic :: Software Development
Classifier: Topic :: Software Development :: Documentation
Classifier: Topic :: Text Processing :: Markup :: reStructuredText
Requires-Dist: docutils
Requires-Dist: sphinx ; extra == "sphinx"
Requires-Dist: packaging ; extra == "strict"
Project-URL: Home, https://github.com/attakei-lab/rst-pypi-ref
Project-URL: Repository, https://github.com/attakei-lab/rst-pypi-ref
Provides-Extra: sphinx
Provides-Extra: strict
